preppy.py
preppy-5.1.0.dist-info/METADATA
preppy-5.1.0.dist-info/WHEEL
preppy-5.1.0.dist-info/entry_points.txt
preppy-5.1.0.dist-info/top_level.txt
preppy-5.1.0.dist-info/RECORD
